MANIFEST.in
README.md
setup.py
PyJOAT.egg-info/PKG-INFO
PyJOAT.egg-info/SOURCES.txt
PyJOAT.egg-info/dependency_links.txt
PyJOAT.egg-info/requires.txt
PyJOAT.egg-info/top_level.txt
joat/__init__.py