Metadata-Version: 1.1
Name: PyJOAT
Version: 1.0.1
Summary: JWT OAuth 2.0 Access Token management
Home-page: https://github.com/rknLA/joat
Author: R. Kevin Nelson
Author-email: kevin@rkn.la
License: MIT
Keywords: joat jwt json web access token oauth
Platform: UNKNOWN
Classifier: Environment :: Web Environment
Classifier: Intended Audience :: Developers
Classifier: Development Status :: 3 - Alpha
Classifier: License :: OSI Approved :: MIT License
Classifier: Programming Language :: Python :: 2.7
Classifier: Topic :: Internet :: WWW/HTTP :: Dynamic Content
Classifier: Topic :: Software Development :: Libraries :: Python Modules
